TransMux/debug.py
transmux-4.2.1.dist-info/METADATA
transmux-4.2.1.dist-info/WHEEL
transmux-4.2.1.dist-info/RECORD
