Metadata-Version: 2.1
Name: transmux
Version: 4.2.1
Summary: My personal tookit.
Author: InEase
Author-email: InEase28@gmail.com
Requires-Python: >=3.8,<4.0
Classifier: Programming Language :: Python :: 3
Classifier: Programming Language :: Python :: 3.8
Classifier: Programming Language :: Python :: 3.9
Classifier: Programming Language :: Python :: 3.10
Classifier: Programming Language :: Python :: 3.11
Classifier: Programming Language :: Python :: 3.12
Requires-Dist: better-exceptions (>=0.3.3,<0.4.0)
